jindanlicai/__init__.py
jindanlicai/base_setting.py
jindanlicai/basic.py
jindanlicai/getValue.py
jindanlicai/htmlTestReportCN.py
jindanlicai/jindanlicai.py
jindanlicai/log.py
jindanlicai-1.0.6.dist-info/METADATA
jindanlicai-1.0.6.dist-info/WHEEL
jindanlicai-1.0.6.dist-info/top_level.txt
jindanlicai-1.0.6.dist-info/zip-safe
jindanlicai-1.0.6.dist-info/RECORD
